odoo/addons/ssi_report_async/README.rst
odoo/addons/ssi_report_async/__init__.py
odoo/addons/ssi_report_async/__manifest__.py
odoo/addons/ssi_report_async/test-requirements.txt
odoo/addons/ssi_report_async/security/ir_rule.xml
odoo/addons/ssi_report_async/static/description/icon.png
odoo/addons/ssi_report_async/views/report_async_admin.xml
odoo/addons/ssi_report_async/views/report_async_all.xml
odoo14_addon_ssi_report_async-14.0.1.0.1.dist-info/METADATA
odoo14_addon_ssi_report_async-14.0.1.0.1.dist-info/WHEEL
odoo14_addon_ssi_report_async-14.0.1.0.1.dist-info/top_level.txt
odoo14_addon_ssi_report_async-14.0.1.0.1.dist-info/RECORD
